{"monsterName":"Gloutovore","monsterId":216,"favoriteSubArea":165,"drops":[{"dropName":"Oueille","dropId":21618,"weight":0},{"dropName":"Pollenectar","dropId":21171,"weight":0},{"dropName":"Glouto Rhum","dropId":2632,"weight":1},{"dropName":"Viande Exsudative","dropId":17140,"weight":3},{"dropName":"Engrais de Moon","dropId":17283,"weight":0},{"dropName":"Fleur de Gloutovore","dropId":2253,"weight":1},{"dropName":"Amulette de Lear","dropId":9528,"weight":0},{"dropName":"Kole","dropId":1018,"weight":1},{"dropName":"Sachet de Résine","dropId":16835,"weight":10}],"subAreas":[165,847]}