{"monsterName":"Gobelin Glouton","monsterId":3376,"favoriteSubArea":0,"drops":[{"dropName":"Sac de Serrefeuille","dropId":13853,"weight":0},{"dropName":"Sac de Persil","dropId":13852,"weight":0},{"dropName":"Sac d'Esdragon","dropId":13855,"weight":0},{"dropName":"Sac de Ciroulette","dropId":13854,"weight":0},{"dropName":"Parchemin Blanc","dropId":679,"weight":1},{"dropName":"Sac d'Esdragon","dropId":13855,"weight":0},{"dropName":"Sac d'Esdragon","dropId":13855,"weight":0},{"dropName":"Sac de Persil","dropId":13852,"weight":0},{"dropName":"Sac d'Esdragon","dropId":13855,"weight":0},{"dropName":"Sac de Ciroulette","dropId":13854,"weight":0},{"dropName":"Sac d'Esdragon","dropId":13855,"weight":0},{"dropName":"Sac de Persil","dropId":13852,"weight":0},{"dropName":"Sac de Persil","dropId":13852,"weight":0},{"dropName":"Sac de Ciroulette","dropId":13854,"weight":0},{"dropName":"Sac de Serrefeuille","dropId":13853,"weight":0},{"dropName":"Sac de Ciroulette","dropId":13854,"weight":0},{"dropName":"Sac de Ciroulette","dropId":13854,"weight":0},{"dropName":"Sac de Persil","dropId":13852,"weight":0},{"dropName":"Sac de Serrefeuille","dropId":13853,"weight":0},{"dropName":"Sac de Serrefeuille","dropId":13853,"weight":0},{"dropName":"Sac de Serrefeuille","dropId":13853,"weight":0},{"dropName":"Sac de Ciroulette","dropId":13854,"weight":0},{"dropName":"Sac de Serrefeuille","dropId":13853,"weight":0},{"dropName":"Sac de Persil","dropId":13852,"weight":0},{"dropName":"Sac d'Esdragon","dropId":13855,"weight":0},{"dropName":"Sac de Serrefeuille","dropId":13853,"weight":0},{"dropName":"Sac d'Esdragon","dropId":13855,"weight":0},{"dropName":"Sac de Serrefeuille","dropId":13853,"weight":0},{"dropName":"Sac de Serrefeuille","dropId":13853,"weight":0},{"dropName":"Parchemin d'Ivoire","dropId":678,"weight":1},{"dropName":"Sac de Persil","dropId":13852,"weight":0},{"dropName":"Sac de Serrefeuille","dropId":13853,"weight":0},{"dropName":"Sac de Ciroulette","dropId":13854,"weight":0},{"dropName":"Parchemin Doré","dropId":680,"weight":1},{"dropName":"Sac d'Esdragon","dropId":13855,"weight":0},{"dropName":"Sac d'Esdragon","dropId":13855,"weight":0},{"dropName":"Sac de Ciroulette","dropId":13854,"weight":0},{"dropName":"Sac d'Esdragon","dropId":13855,"weight":0},{"dropName":"Sac de Persil","dropId":13852,"weight":0},{"dropName":"Sac de Ciroulette","dropId":13854,"weight":0},{"dropName":"Sac de Persil","dropId":13852,"weight":0},{"dropName":"Sac de Persil","dropId":13852,"weight":0},{"dropName":"Sac de Ciroulette","dropId":13854,"weight":0}],"subAreas":[]}